TurnonTech/__init__.py
TurnonTech/old_fucntion.py
TurnonTech/modbusTCP/__init__.py
TurnonTech/modbusTCP/modbusTCP.py
TurnonTech-0.0.3.dist-info/LICENSE
TurnonTech-0.0.3.dist-info/METADATA
TurnonTech-0.0.3.dist-info/WHEEL
TurnonTech-0.0.3.dist-info/top_level.txt
TurnonTech-0.0.3.dist-info/RECORD
